cstl/__init__.py
cstl/_cstl.so
cstl/cstl.py
cstl/version.py
cstl-0.0.5.dist-info/METADATA
cstl-0.0.5.dist-info/WHEEL
cstl-0.0.5.dist-info/top_level.txt
cstl-0.0.5.dist-info/RECORD
