Metadata-Version: 2.1
Name: cstl
Version: 0.0.5
Summary: The C++ Standard Template Library (STL) for Python
Home-page: https://github.com/fuzihaofzh/cstl
Author: 
Author-email: 
License: UNKNOWN
Keywords: C++ STL List Dict Set
Platform: UNKNOWN
Classifier: Programming Language :: Python :: 3.8
